{
  "version": "1.0.2",
  "name": "The Void (FW)",
  "props": [
    {
      "alpha": 1,
      "angle": 0,
      "animType": "sparrow",
      "animations": [      ],
      "assetPath": "stages/void_fw/void_background",
      "blend": "",
      "color": "#FFFFFF",
      "danceEvery": 0,
      "flipX": false,
      "flipY": false,
      "isPixel": false,
      "name": "void_background",
      "position": [
        -1068,
        -632
      ],
      "scale": 3,
      "scroll": [
        1,
        1
      ],
      "startingAnimation": "",
      "zIndex": 0
    },
    {
      "alpha": 1,
      "angle": 0,
      "animType": "sparrow",
      "animations": [      ],
      "assetPath": "stages/void_fw/void_background2",
      "blend": "",
      "color": "#FFFFFF",
      "danceEvery": 0,
      "flipX": false,
      "flipY": false,
      "isPixel": false,
      "name": "void_background2",
      "position": [
        -1072,
        -632
      ],
      "scale": 3,
      "scroll": [
        1,
        1
      ],
      "startingAnimation": "",
      "zIndex": 0
    },
    {
      "alpha": 1,
      "angle": 0,
      "animType": "sparrow",
      "animations": [      ],
      "assetPath": "stages/void_fw/back_glitch1",
      "blend": "",
      "color": "#FFFFFF",
      "danceEvery": 0,
      "flipX": false,
      "flipY": false,
      "isPixel": false,
      "name": "back_glitch1",
      "position": [
        -1528,
        -838
      ],
      "scale": 1.65,
      "scroll": [
        1,
        1
      ],
      "startingAnimation": "",
      "zIndex": 0
    },
    {
      "alpha": 1,
      "angle": 0,
      "animType": "sparrow",
      "animations": [      ],
      "assetPath": "stages/void_fw/void_house",
      "blend": "",
      "color": "#FFFFFF",
      "danceEvery": 0,
      "flipX": false,
      "flipY": false,
      "isPixel": false,
      "name": "void_house",
      "position": [
        -402,
        -394
      ],
      "scale": 1.85,
      "scroll": [
        1,
        1
      ],
      "startingAnimation": "",
      "zIndex": 1
    },
    {
      "alpha": 1,
      "angle": 0,
      "animType": "sparrow",
      "animations": [      ],
      "assetPath": "stages/void_fw/void_floor",
      "blend": "",
      "color": "#FFFFFF",
      "danceEvery": 0,
      "flipX": false,
      "flipY": false,
      "isPixel": false,
      "name": "void_floor",
      "position": [
        -809,
        -626
      ],
      "scale": 2.5,
      "scroll": [
        1,
        1
      ],
      "startingAnimation": "",
      "zIndex": 1
    },
    {
      "alpha": 1,
      "angle": 0,
      "animType": "sparrow",
      "animations": [      ],
      "assetPath": "stages/void_fw/void_stuff1",
      "blend": "",
      "color": "#FFFFFF",
      "danceEvery": 0,
      "flipX": false,
      "flipY": false,
      "isPixel": false,
      "name": "void_stuff1",
      "position": [
        536,
        -90
      ],
      "scale": 1,
      "scroll": [
        1,
        1
      ],
      "startingAnimation": "",
      "zIndex": 2
    },
    {
      "alpha": 1,
      "angle": 0,
      "animType": "sparrow",
      "animations": [      ],
      "assetPath": "stages/void_fw/void_stuff3",
      "blend": "",
      "color": "#FFFFFF",
      "danceEvery": 0,
      "flipX": false,
      "flipY": false,
      "isPixel": false,
      "name": "void_stuff3",
      "position": [
        -762,
        -14
      ],
      "scale": 1,
      "scroll": [
        1,
        1
      ],
      "startingAnimation": "",
      "zIndex": 3
    },
    {
      "alpha": 1,
      "angle": 0,
      "animType": "sparrow",
      "animations": [      ],
      "assetPath": "stages/void_fw/void_stuff2",
      "blend": "",
      "color": "#FFFFFF",
      "danceEvery": 0,
      "flipX": false,
      "flipY": false,
      "isPixel": false,
      "name": "void_stuff2",
      "position": [
        624,
        688
      ],
      "scale": 1,
      "scroll": [
        1,
        1
      ],
      "startingAnimation": "",
      "zIndex": 3
    },
    {
      "alpha": 1,
      "angle": 0,
      "animType": "sparrow",
      "animations": [      ],
      "assetPath": "stages/void_fw/void_stuff4",
      "blend": "",
      "color": "#FFFFFF",
      "danceEvery": 0,
      "flipX": false,
      "flipY": false,
      "isPixel": false,
      "name": "void_stuff4",
      "position": [
        -568,
        -278
      ],
      "scale": 2,
      "scroll": [
        1,
        1
      ],
      "startingAnimation": "",
      "zIndex": 4
    },
    {
      "alpha": 0,
      "angle": 0,
      "animType": "sparrow",
      "animations": [      ],
      "assetPath": "stages/void_fw/back_glitch2",
      "blend": "",
      "color": "#FFFFFF",
      "danceEvery": 0,
      "flipX": false,
      "flipY": false,
      "isPixel": false,
      "name": "back_glitch2",
      "position": [
        -1066,
        82
      ],
      "scale": [
	1.25,
	1.05
],
      "scroll": [
        1,
        1
      ],
      "startingAnimation": "",
      "zIndex": 5
    },
    {
      "alpha": 1,
      "angle": 0,
      "animType": "sparrow",
      "animations": [      ],
      "assetPath": "stages/void_fw/front_glitch1",
      "blend": "",
      "color": "#FFFFFF",
      "danceEvery": 0,
      "flipX": false,
      "flipY": false,
      "isPixel": false,
      "name": "front_glitch1",
      "position": [
        -856,
        -288
      ],
      "scale": 1,
      "scroll": [
        1,
        1
      ],
      "startingAnimation": "",
      "zIndex": 6
    },
    {
      "alpha": 0,
      "angle": 0,
      "animType": "sparrow",
      "animations": [      ],
      "assetPath": "stages/void_fw/front_glitch2",
      "blend": "",
      "color": "#FFFFFF",
      "danceEvery": 0,
      "flipX": false,
      "flipY": false,
      "isPixel": false,
      "name": "front_glitch2",
      "position": [
        -860,
        -308
      ],
      "scale": 1,
      "scroll": [
        1,
        1
      ],
      "startingAnimation": "",
      "zIndex": 7
    },
    {
      "alpha": 0,
      "angle": 0,
      "animType": "sparrow",
      "animations": [      ],
      "assetPath": "stages/void_fw/corrupt_house",
      "blend": "",
      "color": "#FFFFFF",
      "danceEvery": 0,
      "flipX": false,
      "flipY": false,
      "isPixel": false,
      "name": "corrupt_house",
      "position": [
        -730,
        -528
      ],
      "scale": 1,
      "scroll": [
        1,
        1
      ],
      "startingAnimation": "",
      "zIndex": 8
    },
    {
      "alpha": 0,
      "angle": 0,
      "animType": "sparrow",
      "animations": [      ],
      "assetPath": "stages/void_fw/corrupt_bottom_glitch",
      "blend": "",
      "color": "#FFFFFF",
      "danceEvery": 0,
      "flipX": false,
      "flipY": false,
      "isPixel": false,
      "name": "corrupt_bottom_glitch",
      "position": [
        -1100,
        -250
      ],
      "scale": 1.25,
      "scroll": [
        1,
        1
      ],
      "startingAnimation": "",
      "zIndex": 405
    },
    {
      "alpha": 0,
      "angle": 0,
      "animType": "sparrow",
      "animations": [      ],
      "assetPath": "stages/void_fw/corrupt_purple_bottom",
      "blend": "",
      "color": "#FFFFFF",
      "danceEvery": 0,
      "flipX": false,
      "flipY": false,
      "isPixel": false,
      "name": "corrupt_purple_bottom",
      "position": [
        -1078,
        -46
      ],
      "scale": [
	1.25,
	1.1
],
      "scroll": [
        1,
        1
      ],
      "startingAnimation": "",
      "zIndex": 406
    },
    {
      "alpha": 0,
      "angle": 0,
      "animType": "sparrow",
      "animations": [      ],
      "assetPath": "stages/void_fw/corrupt_white_top",
      "blend": "",
      "color": "#FFFFFF",
      "danceEvery": 0,
      "flipX": false,
      "flipY": false,
      "isPixel": false,
      "name": "corrupt_white_top",
      "position": [
        -1088,
        -630
      ],
      "scale": [
	1.25,
	1
],
      "scroll": [
        1,
        1
      ],
      "startingAnimation": "",
      "zIndex": 407
    }
  ],
  "characters": {
    "bf": {
      "alpha": 1,
      "angle": 0,
      "cameraOffsets": [
        56,
        34
      ],
      "position": [
        1050.75,
        886.5
      ],
      "scale": 1,
      "scroll": [
        1,
        1
      ],
      "zIndex": 300
    },
    "dad": {
      "alpha": 1,
      "angle": 0,
      "cameraOffsets": [
        192,
        -38
      ],
      "position": [
        105.78,
        861.96
      ],
      "scale": 1.2,
      "scroll": [
        1,
        1
      ],
      "zIndex": 200
    },
    "gf": {
      "alpha": 0,
      "angle": 0,
      "cameraOffsets": [
        0,
        0
      ],
      "position": [
        1005.5,
        810.5
      ],
      "scale": 1,
      "scroll": [
        1,
        1
      ],
      "zIndex": 300
    }
  },
  "cameraZoom": 0.85,
  "directory": "shared"
}